easychrono/__init__.py
easychrono/database.py
easychrono/formatter.py
easychrono/operations.py
easychrono/parser.py
easychrono/utils.py
test/__init__.py
test/test.py
easychrono-0.1.4.dist-info/LICENSE
easychrono-0.1.4.dist-info/METADATA
easychrono-0.1.4.dist-info/WHEEL
easychrono-0.1.4.dist-info/top_level.txt
easychrono-0.1.4.dist-info/RECORD
