Metadata-Version: 2.1
Name: easychrono
Version: 0.1.4
Summary: A Python package for working with timedelta objects and more
Home-page: https://github.com/legendofpokemon/easychrono
Author: Alexander Roberts
Author-email: alex.roberts@live.ca
Classifier: Programming Language :: Python :: 3
Classifier: License :: OSI Approved :: MIT License
Classifier: Operating System :: OS Independent
Requires-Python: >=3.6
License-File: LICENSE
Provides-Extra: testing
Requires-Dist: pytest; extra == "testing"
